aia_protocol/__init__.py
aia_protocol/core/__init__.py
aia_protocol/core/callback.py
aia_protocol/core/frame_manager.py
aia_protocol/core/message.py
aia_protocol/core/protocol_engine.py
aia_protocol/core/responder_registry.py
aia_protocol/core/server_socket.py
aia_protocol/pipeline/__init__.py
aia_protocol/pipeline/base_stage.py
aia_protocol/pipeline/checksum_stage.py
aia_protocol/pipeline/compression_stage.py
aia_protocol/pipeline/encryption_stage.py
aia_protocol/pipeline/pipeline.py
aia_protocol/transport/__init__.py
aia_protocol/transport/base.py
aia_protocol/transport/udp_transport.py
aia_protocol-0.0.1.dist-info/METADATA
aia_protocol-0.0.1.dist-info/WHEEL
aia_protocol-0.0.1.dist-info/top_level.txt
aia_protocol-0.0.1.dist-info/RECORD
