Metadata-Version: 2.4
Name: aia-protocol
Version: 0.0.1
Requires-Python: >=3.9
Requires-Dist: cryptography>=44.0.3
Dynamic: requires-dist
Dynamic: requires-python
